pop_llm/__init__.py
pop_llm/chat_agent.py
pop_llm/pop.py
pop_llm/prompts.py
pop_llm-0.0.7.dist-info/LICENSE
pop_llm-0.0.7.dist-info/METADATA
pop_llm-0.0.7.dist-info/WHEEL
pop_llm-0.0.7.dist-info/top_level.txt
pop_llm-0.0.7.dist-info/RECORD
