Metadata-Version: 2.1
Name: pop-llm
Version: 0.0.7
Summary: A Python library for Prompt Oriented Programming with Large Language Models
Author-email: Yibo Wei <david_wyb2001@outlook.com>
Project-URL: Homepage, https://github.com/Microwave_WYB/POP
Classifier: Programming Language :: Python :: 3
Classifier: License :: OSI Approved :: MIT License
Classifier: Operating System :: OS Independent
Requires-Python: >=3.7
License-File: LICENSE
Requires-Dist: tiktoken
Requires-Dist: openai
